[
    {
      "description": "  Login to D3A.io\n  Create a Project\n  Create a Simulation",
      "keyword": "Feature",
      "name": "d3a.io",
      "line": 1,
      "id": "d3a.io",
      "tags": [],
      "uri": "d3a.feature",
      "elements": [
        {
          "id": "d3a.io;validate-that-a-precreated-user-is-able-to-login-to-d3a.io",
          "keyword": "Scenario",
          "line": 7,
          "name": "Validate that a precreated user is able to login to d3a.io",
          "tags": [
            {
              "name": "@login",
              "line": 6
            }
          ],
          "type": "scenario",
          "steps": [
            {
              "arguments": [],
              "keyword": "Given ",
              "line": 8,
              "name": "I open D3A.io login page",
              "result": {
                "status": "passed",
                "duration": 7354000000
              }
            },
            {
              "arguments": [],
              "keyword": "And ",
              "line": 9,
              "name": "I check page contains \"Create new account\" and \"Request password reset\" links",
              "result": {
                "status": "passed",
                "duration": 253000000
              }
            },
            {
              "arguments": [],
              "keyword": "And ",
              "line": 10,
              "name": "I enter \"krishna.x.kant@icloud.com\" in the email field",
              "result": {
                "status": "passed",
                "duration": 1036000000
              }
            },
            {
              "arguments": [],
              "keyword": "And ",
              "line": 11,
              "name": "I enter \"krishna.x.kant#123\" in the password field",
              "result": {
                "status": "passed",
                "duration": 764000000
              }
            },
            {
              "arguments": [],
              "keyword": "When ",
              "line": 12,
              "name": "I click on login button",
              "result": {
                "status": "passed",
                "duration": 236000000
              }
            },
            {
              "arguments": [],
              "keyword": "Then ",
              "line": 13,
              "name": "I should navigate to homepage",
              "result": {
                "status": "passed",
                "duration": 1003000000
              }
            },
            {
              "arguments": [],
              "keyword": "Then ",
              "line": 14,
              "name": "I check setting menu to check \"krishna.x.kant@icloud.com\" user is logged in",
              "result": {
                "status": "passed",
                "duration": 28000000
              }
            },
            {
              "arguments": [],
              "keyword": "Then ",
              "line": 15,
              "name": "I check all the navigation items on left menu are present",
              "result": {
                "status": "passed",
                "duration": 405000000
              }
            },
            {
              "arguments": [],
              "keyword": "Then ",
              "line": 16,
              "name": "I check all the video items on the page are present",
              "result": {
                "status": "passed",
                "duration": 3786000000
              }
            }
          ]
        },
        {
          "id": "d3a.io;validate-that-a-logged-in-user-is-able-to-create-a-project-and-its-listed-correctly-after-creation",
          "keyword": "Scenario",
          "line": 20,
          "name": "Validate that a logged in user is able to create a project and its listed correctly after creation",
          "tags": [
            {
              "name": "@create-project",
              "line": 19
            }
          ],
          "type": "scenario",
          "steps": [
            {
              "arguments": [],
              "keyword": "Given ",
              "line": 21,
              "name": "I check setting menu to confirm \"krishna.x.kant@icloud.com\" user is logged in",
              "result": {
                "status": "passed",
                "duration": 1115000000
              }
            },
            {
              "arguments": [],
              "keyword": "When ",
              "line": 22,
              "name": "I click on Projects menu on left to create new project",
              "result": {
                "status": "passed",
                "duration": 173000000
              }
            },
            {
              "arguments": [],
              "keyword": "Then ",
              "line": 23,
              "name": "I should navigate to Projects page",
              "result": {
                "status": "passed",
                "duration": 12000000
              }
            },
            {
              "arguments": [],
              "keyword": "Then ",
              "line": 24,
              "name": "I click on New Project button on top right",
              "result": {
                "status": "passed",
                "duration": 321000000
              }
            },
            {
              "arguments": [],
              "keyword": "Then ",
              "line": 25,
              "name": "I provide \"Test Project #\" as name and \"This is sample project for demo\" as description for the new project",
              "result": {
                "status": "passed",
                "duration": 1327000000
              }
            },
            {
              "arguments": [],
              "keyword": "When ",
              "line": 26,
              "name": "I click on Add button to create new project",
              "result": {
                "status": "passed",
                "duration": 154000000
              }
            },
            {
              "arguments": [],
              "keyword": "Then ",
              "line": 27,
              "name": "I check that new project is created and is listed correctly",
              "result": {
                "status": "passed",
                "duration": 2093000000
              }
            }
          ]
        },
        {
          "id": "d3a.io;validate-that-a-logged-in-user-can-create-a-simulation-and-its-listed-correctly,-simulation-can-be-empty",
          "keyword": "Scenario",
          "line": 31,
          "name": "Validate that a logged in user can create a simulation and its listed correctly, simulation can be empty",
          "tags": [
            {
              "name": "@create-simulation",
              "line": 30
            }
          ],
          "type": "scenario",
          "steps": [
            {
              "arguments": [],
              "keyword": "Given ",
              "line": 32,
              "name": "I check setting menu to confirm \"krishna.x.kant@icloud.com\" user is logged in",
              "result": {
                "status": "passed",
                "duration": 105000000
              }
            },
            {
              "arguments": [],
              "keyword": "Then ",
              "line": 33,
              "name": "I click on newly created project",
              "result": {
                "status": "passed",
                "duration": 211000000
              }
            },
            {
              "arguments": [],
              "keyword": "Then ",
              "line": 34,
              "name": "I click on New Simultaion button to add simulation",
              "result": {
                "status": "passed",
                "duration": 127000000
              }
            },
            {
              "arguments": [],
              "keyword": "Then ",
              "line": 35,
              "name": "I check that new simulation form is opened and I validate all form elements",
              "result": {
                "status": "passed",
                "duration": 645000000
              }
            },
            {
              "arguments": [],
              "keyword": "Then ",
              "line": 36,
              "name": "I provide the simulation description as \"This is sample simulation for demo\" and leave rest of the values default on form",
              "result": {
                "status": "passed",
                "duration": 792000000
              }
            },
            {
              "arguments": [],
              "keyword": "Then ",
              "line": 37,
              "name": "I click on Next button to create new simulation",
              "result": {
                "status": "passed",
                "duration": 117000000
              }
            },
            {
              "arguments": [],
              "keyword": "Then ",
              "line": 38,
              "name": "I check that new simulation is created and is listed correctly",
              "result": {
                "status": "passed",
                "duration": 749000000
              }
            }
          ]
        }
      ]
    }
  ]